ai_feedback/__init__.py
ai_feedback/__main__.py
ai_feedback/code_processing.py
ai_feedback/data/output/response_and_prompt.md
ai_feedback/data/output/response_only.md
ai_feedback/data/output/verbose.md
ai_feedback/data/prompts/system/code_feedback_v3.md
ai_feedback/data/prompts/system/code_grader.md
ai_feedback/data/prompts/system/code_test_feedback.md
ai_feedback/data/prompts/system/image_comparison_grader.md
ai_feedback/data/prompts/system/image_style_grader.md
ai_feedback/data/prompts/system/student_test_feedback.md
ai_feedback/data/prompts/system/text_feedback_v3.md
ai_feedback/data/prompts/user/code_annotation.md
ai_feedback/data/prompts/user/code_explanation.md
ai_feedback/data/prompts/user/code_feedback_r1.md
ai_feedback/data/prompts/user/code_feedback_v3.md
ai_feedback/data/prompts/user/code_functionality.md
ai_feedback/data/prompts/user/code_hint.md
ai_feedback/data/prompts/user/code_lines.md
ai_feedback/data/prompts/user/code_overall.md
ai_feedback/data/prompts/user/code_overall_with_instruction.md
ai_feedback/data/prompts/user/code_table.md
ai_feedback/data/prompts/user/code_template.md
ai_feedback/data/prompts/user/code_test_feedback.md
ai_feedback/data/prompts/user/image_analyze.md
ai_feedback/data/prompts/user/image_analyze_annotations.md
ai_feedback/data/prompts/user/image_compare.md
ai_feedback/data/prompts/user/image_compare_overall.md
ai_feedback/data/prompts/user/image_compare_with_instruction.md
ai_feedback/data/prompts/user/image_overall.md
ai_feedback/data/prompts/user/image_overall_with_instruction.md
ai_feedback/data/prompts/user/image_style.md
ai_feedback/data/prompts/user/image_style_annotations.md
ai_feedback/data/prompts/user/text_analyze_r1.md
ai_feedback/data/prompts/user/text_analyze_v3.md
ai_feedback/data/prompts/user/text_eft_proof.md
ai_feedback/data/prompts/user/text_pdf_analyze.md
ai_feedback/data/schema/code_annotation_schema.json
ai_feedback/data/schema/image_annotation_schema.json
ai_feedback/data/schema/tags_schema.json
markus_ai_feedback-0.1.0.dist-info/licenses/LICENSE
markus_ai_feedback-0.1.0.dist-info/WHEEL
markus_ai_feedback-0.1.0.dist-info/entry_points.txt
markus_ai_feedback-0.1.0.dist-info/METADATA
markus_ai_feedback-0.1.0.dist-info/RECORD
