Metadata-Version: 2.4
Name: markus-ai-feedback
Version: 0.1.0
Summary: A package for generating AI feedback on student work
Author: Ricky Chen, Sohee Goo, Rolland He, Mateo Naranjo, Will Kukkamalla, Nathan Taback, Donny Wong
License-Expression: MIT
License-File: LICENSE
Classifier: Programming Language :: Python :: 3
Classifier: Operating System :: OS Independent
Requires-Dist: anthropic
Requires-Dist: dotenv
Requires-Dist: matplotlib
Requires-Dist: nbformat
Requires-Dist: ollama
Requires-Dist: openai
Requires-Dist: pillow
Requires-Dist: pymupdf
Requires-Dist: pypdf2
Requires-Dist: requests
Maintainer: David Liu
Maintainer-email: David Liu <david@cs.toronto.edu>
Requires-Python: >=3.9
Project-URL: Homepage, https://github.com/MarkUsProject/ai-autograding-feedback/
Project-URL: Issues, https://github.com/MarkUsProject/ai-autograding-feedback/issues
